ai_cli/__init__.py
ai_cli/cli/__init__.py
ai_cli/cli/app.py
ai_cli/cli/context.py
ai_cli/cli/main.py
ai_cli/cli/handlers/__init__.py
ai_cli/cli/handlers/config_cmd.py
ai_cli/cli/handlers/create_pr.py
ai_cli/cli/handlers/create_repo.py
ai_cli/cli/handlers/smart_commit.py
ai_cli/cli/handlers/smart_commit_all.py
ai_cli/cli/ui/__init__.py
ai_cli/cli/ui/console.py
ai_cli/cli/ui/errors.py
ai_cli/cli/ui/model_select.py
ai_cli/cli/ui/panels.py
ai_cli/cli/ui/prompts.py
ai_cli/cli/ui/provider_select.py
ai_cli/clients/__init__.py
ai_cli/clients/anthropic.py
ai_cli/clients/gemini.py
ai_cli/clients/local.py
ai_cli/clients/openai.py
ai_cli/config/__init__.py
ai_cli/config/cache.py
ai_cli/config/loader.py
ai_cli/config/paths.py
ai_cli/config/profiles.py
ai_cli/config/prompts.py
ai_cli/config/settings.py
ai_cli/config/writer.py
ai_cli/core/__init__.py
ai_cli/core/exceptions.py
ai_cli/core/common/enums.py
ai_cli/core/interfaces/__init__.py
ai_cli/core/interfaces/ai_service.py
ai_cli/core/interfaces/git_repository.py
ai_cli/core/interfaces/pull_request_service.py
ai_cli/core/interfaces/repository.py
ai_cli/core/models/__init__.py
ai_cli/core/models/commit_message.py
ai_cli/core/models/file_change.py
ai_cli/core/models/file_group.py
ai_cli/core/models/git_branch.py
ai_cli/core/models/git_diff.py
ai_cli/core/models/pr_context.py
ai_cli/core/models/pull_request.py
ai_cli/core/models/repository.py
ai_cli/infrastructure/__init__.py
ai_cli/infrastructure/git_repository.py
ai_cli/infrastructure/pr_service.py
ai_cli/infrastructure/repo_service.py
ai_cli/pipelines/__init__.py
ai_cli/pipelines/commit_message.py
ai_cli/pipelines/common.py
ai_cli/pipelines/file_correlation.py
ai_cli/services/__init__.py
ai_cli/services/create_pr_service.py
ai_cli/services/pr_context_builder.py
ai_cli/services/smart_commit_all_service.py
ai_cli/services/smart_commit_service.py
parcky_cli-2026.6.0a4.dist-info/METADATA
parcky_cli-2026.6.0a4.dist-info/WHEEL
parcky_cli-2026.6.0a4.dist-info/entry_points.txt
parcky_cli-2026.6.0a4.dist-info/licenses/LICENSE
parcky_cli-2026.6.0a4.dist-info/RECORD
