Metadata-Version: 2.4
Name: parcky-cli
Version: 2026.6.0a4
Summary: AI-powered git commit and PR creation tool
Author: Jose Carlos da SIlva Filho
License-File: LICENSE
Keywords: ai,automation,commit,git,pull-request
Classifier: Development Status :: 4 - Beta
Classifier: Intended Audience :: Developers
Classifier: License :: OSI Approved :: MIT License
Classifier: Programming Language :: Python :: 3
Classifier: Programming Language :: Python :: 3.9
Classifier: Programming Language :: Python :: 3.10
Classifier: Programming Language :: Python :: 3.11
Classifier: Programming Language :: Python :: 3.12
Classifier: Topic :: Software Development :: Version Control :: Git
Requires-Python: >=3.13
Requires-Dist: google-genai>=1.47.0
Requires-Dist: hatchling>=1.27.0
Requires-Dist: prompt-toolkit>=3.0
Requires-Dist: pydantic-settings>=2.11.0
Requires-Dist: rich>=14.2.0
Requires-Dist: ruff>=0.14.11
Requires-Dist: taskipy>=1.14.1
Requires-Dist: typer>=0.21.1
Provides-Extra: dev
Requires-Dist: mypy>=1.0.0; extra == 'dev'
Requires-Dist: pre-commit>=3.0.0; extra == 'dev'
Requires-Dist: pytest-cov>=4.0.0; extra == 'dev'
Requires-Dist: pytest>=7.0.0; extra == 'dev'
Requires-Dist: ruff>=0.8.0; extra == 'dev'
Provides-Extra: tui
Requires-Dist: prompt-toolkit>=3.0; extra == 'tui'
